MediaStationBitmapRle.cpython-311-x86_64-linux-musl.so
MediaStationImaAdpcm.cpython-311-x86_64-linux-musl.so
MediaStation/System.py
MediaStation/Engine.py
MediaStation/__init__.py
MediaStation/Profile.py
MediaStation/Context.py
MediaStation/global_variables.py
MediaStation/Riff/DataFile.py
MediaStation/Riff/Chunk.py
MediaStation/Riff/SubFile.py
MediaStation/Assets/Bitmap.py
MediaStation/Assets/__init__.py
MediaStation/Assets/BitmapSet.py
MediaStation/Assets/BitmapRle.c
MediaStation/Assets/Sprite.py
MediaStation/Assets/Sound.py
MediaStation/Assets/Script.py
MediaStation/Assets/Movie.py
MediaStation/Assets/Asset.py
MediaStation/Assets/ImaAdpcm.c
MediaStation/Assets/Font.py
MediaStation/Assets/Text.py
MediaStation/Primitives/Point.py
MediaStation/Primitives/Reference.py
MediaStation/Primitives/Datum.py
MediaStation/Primitives/Polygon.py
MediaStation/Primitives/BoundingBox.py
MediaStation-0.9.4.dist-info/WHEEL
MediaStation-0.9.4.dist-info/COPYING
MediaStation-0.9.4.dist-info/top_level.txt
MediaStation-0.9.4.dist-info/entry_points.txt
MediaStation-0.9.4.dist-info/RECORD
MediaStation-0.9.4.dist-info/METADATA
