Metadata-Version: 2.1
Name: MediaStation
Version: 0.9.4
Summary: Tools for extracting assets from Media Station, Inc. CD-ROM titles (including Disney's Animated Storybook)
Author: Nathanael Gentry
License:                     GNU GENERAL PUBLIC LICENSE
Project-URL: Homepage, https://github.com/npjg/MediaStation
Project-URL: Repository, https://github.com/npjg/MediaStation
Keywords: disney,reverse-engineering
Classifier: License :: OSI Approved :: MIT License
Classifier: Programming Language :: Python
Classifier: Programming Language :: Python :: 3
Requires-Python: >=3.9
License-File: COPYING
Requires-Dist: self_documenting_struct==0.9.2
Requires-Dist: asset_extraction_framework==0.9.7
